{
  "creatures" :
  [
    {
      "ushort": "index",
      "string": "name",
      "string__1": "description",
      "ushort__1": "coin",
      "ushort__2": "hp",
      "ushort__3": "mp",
      "ushort__4": "ap",
      "ushort__5": "exp",
      "ushort__6": "attack",
      "ushort__7": "defence",
      "bool": "useSkill",
      "[ushort]": "skill index"
    },
    {
      "ushort": 101,
      "string": "몬스터 101",
      "string__1": "테스트 몬스터 101입니다.",
      "ushort__1": 1,
      "ushort__2": 10,
      "ushort__3": 10,
      "ushort__4": 2,
      "ushort__5": 10,
      "ushort__6": 1,
      "ushort__7": 1,
      "bool": "FALSE",
      "[ushort]": ""
    },
    {
      "ushort": 102,
      "string": "몬스터 102",
      "string__1": "테스트 몬스터 102입니다.",
      "ushort__1": 1,
      "ushort__2": 10,
      "ushort__3": 10,
      "ushort__4": 2,
      "ushort__5": 10,
      "ushort__6": 1,
      "ushort__7": 1,
      "bool": "FALSE",
      "[ushort]": ""
    },
    {
      "ushort": 103,
      "string": "몬스터 103",
      "string__1": "테스트 몬스터 103입니다.",
      "ushort__1": 1,
      "ushort__2": 10,
      "ushort__3": 10,
      "ushort__4": 2,
      "ushort__5": 10,
      "ushort__6": 1,
      "ushort__7": 1,
      "bool": "FALSE",
      "[ushort]": ""
    },
    {
      "ushort": 104,
      "string": "몬스터 104",
      "string__1": "테스트 몬스터 104입니다.",
      "ushort__1": 1,
      "ushort__2": 10,
      "ushort__3": 10,
      "ushort__4": 2,
      "ushort__5": 10,
      "ushort__6": 1,
      "ushort__7": 1,
      "bool": "FALSE",
      "[ushort]": ""
    },
    {
      "ushort": 105,
      "string": "몬스터 105",
      "string__1": "테스트 몬스터 105입니다.",
      "ushort__1": 1,
      "ushort__2": 10,
      "ushort__3": 10,
      "ushort__4": 2,
      "ushort__5": 10,
      "ushort__6": 1,
      "ushort__7": 1,
      "bool": "FALSE",
      "[ushort]": ""
    },
    {
      "ushort": 106,
      "string": "몬스터 106",
      "string__1": "테스트 몬스터 106입니다.",
      "ushort__1": 1,
      "ushort__2": 10,
      "ushort__3": 10,
      "ushort__4": 2,
      "ushort__5": 10,
      "ushort__6": 1,
      "ushort__7": 1,
      "bool": "FALSE",
      "[ushort]": ""
    },
    {
      "ushort": 107,
      "string": "몬스터 107",
      "string__1": "테스트 몬스터 107입니다.",
      "ushort__1": 1,
      "ushort__2": 10,
      "ushort__3": 10,
      "ushort__4": 2,
      "ushort__5": 10,
      "ushort__6": 1,
      "ushort__7": 1,
      "bool": "FALSE",
      "[ushort]": ""
    },
    {
      "ushort": 108,
      "string": "몬스터 108",
      "string__1": "테스트 몬스터 108입니다.",
      "ushort__1": 1,
      "ushort__2": 10,
      "ushort__3": 10,
      "ushort__4": 2,
      "ushort__5": 10,
      "ushort__6": 1,
      "ushort__7": 1,
      "bool": "FALSE",
      "[ushort]": ""
    },
    {
      "ushort": 109,
      "string": "몬스터 109",
      "string__1": "테스트 몬스터 109입니다.",
      "ushort__1": 1,
      "ushort__2": 10,
      "ushort__3": 10,
      "ushort__4": 2,
      "ushort__5": 10,
      "ushort__6": 1,
      "ushort__7": 1,
      "bool": "FALSE",
      "[ushort]": ""
    },
    {
      "ushort": 110,
      "string": "몬스터 110",
      "string__1": "테스트 몬스터 110입니다.",
      "ushort__1": 1,
      "ushort__2": 10,
      "ushort__3": 10,
      "ushort__4": 2,
      "ushort__5": 10,
      "ushort__6": 1,
      "ushort__7": 1,
      "bool": "FALSE",
      "[ushort]": ""
    }
  ]
}